hellodude.py
hellodude-0.0.2.dist-info/LICENSE.txt
hellodude-0.0.2.dist-info/METADATA
hellodude-0.0.2.dist-info/WHEEL
hellodude-0.0.2.dist-info/top_level.txt
hellodude-0.0.2.dist-info/RECORD
